mlscorecheck/__init__.py
mlscorecheck/_version.py
mlscorecheck/aggregated/__init__.py
mlscorecheck/aggregated/_check_aggregated_scores.py
mlscorecheck/aggregated/_dataset.py
mlscorecheck/aggregated/_evaluation.py
mlscorecheck/aggregated/_experiment.py
mlscorecheck/aggregated/_fold.py
mlscorecheck/aggregated/_fold_enumeration.py
mlscorecheck/aggregated/_folding.py
mlscorecheck/aggregated/_folding_utils.py
mlscorecheck/aggregated/_generate_problems.py
mlscorecheck/aggregated/_linear_programming.py
mlscorecheck/aggregated/_utils.py
mlscorecheck/check/__init__.py
mlscorecheck/check/binary/__init__.py
mlscorecheck/check/binary/_check_1_dataset_kfold_som.py
mlscorecheck/check/binary/_check_1_dataset_known_folds_mos.py
mlscorecheck/check/binary/_check_1_dataset_unknown_folds_mos.py
mlscorecheck/check/binary/_check_1_testset_no_kfold.py
mlscorecheck/check/binary/_check_n_datasets_mos_kfold_som.py
mlscorecheck/check/binary/_check_n_datasets_mos_known_folds_mos.py
mlscorecheck/check/binary/_check_n_datasets_mos_unknown_folds_mos.py
mlscorecheck/check/binary/_check_n_datasets_som_kfold_som.py
mlscorecheck/check/binary/_check_n_testsets_mos_no_kfold.py
mlscorecheck/check/binary/_check_n_testsets_som_no_kfold.py
mlscorecheck/check/bundles/__init__.py
mlscorecheck/check/bundles/ehg/__init__.py
mlscorecheck/check/bundles/ehg/_tpehg.py
mlscorecheck/check/bundles/retina/__init__.py
mlscorecheck/check/bundles/retina/_chasedb1.py
mlscorecheck/check/bundles/retina/_diaretdb0.py
mlscorecheck/check/bundles/retina/_diaretdb1.py
mlscorecheck/check/bundles/retina/_drishti_gs.py
mlscorecheck/check/bundles/retina/_drive.py
mlscorecheck/check/bundles/retina/_hrf.py
mlscorecheck/check/bundles/retina/_stare.py
mlscorecheck/check/bundles/skinlesion/__init__.py
mlscorecheck/check/bundles/skinlesion/_isic2016.py
mlscorecheck/check/bundles/skinlesion/_isic2017.py
mlscorecheck/check/multiclass/__init__.py
mlscorecheck/check/multiclass/_check_1_dataset_known_folds_mos_macro.py
mlscorecheck-1.0.3.dist-info/LICENSE
mlscorecheck-1.0.3.dist-info/METADATA
mlscorecheck-1.0.3.dist-info/WHEEL
mlscorecheck-1.0.3.dist-info/top_level.txt
mlscorecheck-1.0.3.dist-info/RECORD
