Metadata-Version: 2.1
Name: mlscorecheck
Version: 1.0.3
Summary: ML score check: checking the validity of machine learning and computer vision scores
Home-page: https://github.com/gykovacs/mlscorecheck
Download-URL: https://github.com/gykovacs/mlscorecheck
Author: Gyorgy Kovacs
Author-email: gyuriofkovacs@gmail.com
Maintainer: Gyorgy Kovacs
Maintainer-email: gyuriofkovacs@gmail.com
License: MIT
Classifier: Intended Audience :: Science/Research
Classifier: Intended Audience :: Developers
Classifier: Development Status :: 3 - Alpha
Classifier: License :: OSI Approved :: MIT License
Classifier: Programming Language :: Python
Classifier: Topic :: Scientific/Engineering :: Artificial Intelligence
Classifier: Topic :: Software Development
Classifier: Operating System :: Microsoft :: Windows
Classifier: Operating System :: POSIX
Classifier: Operating System :: Unix
Classifier: Operating System :: MacOS
Requires-Python: >=3.5
License-File: LICENSE
Requires-Dist: numpy
Requires-Dist: scipy
Requires-Dist: scikit-learn
Requires-Dist: pulp
Provides-Extra: docs
Requires-Dist: sphinx ; extra == 'docs'
Requires-Dist: sphinx-gallery ; extra == 'docs'
Requires-Dist: sphinx-rtd-theme ; extra == 'docs'
Requires-Dist: matplotlib ; extra == 'docs'
Requires-Dist: pandas ; extra == 'docs'
Requires-Dist: pulp ; extra == 'docs'
Provides-Extra: tests
Requires-Dist: pytest ; extra == 'tests'
